quota_notifier/__init__.py
quota_notifier/__main__.py
quota_notifier/cli.py
quota_notifier/data/template.html
quota_notifier/disk_utils.py
quota_notifier/notify.py
quota_notifier/orm.py
quota_notifier/settings.py
quota_notifier/shell.py
quota_notifier-0.6.6.dist-info/LICENSE.md
quota_notifier-0.6.6.dist-info/METADATA
quota_notifier-0.6.6.dist-info/WHEEL
quota_notifier-0.6.6.dist-info/entry_points.txt
quota_notifier-0.6.6.dist-info/RECORD
