Metadata-Version: 2.3
Name: quota-notifier
Version: 0.6.6
Summary: Automatic email notification tool for disk quota usage.
Keywords: disk,usage,quota,notify,email
Author: Pitt Center for Research Computing
Requires-Python: >=3.9
Classifier: Environment :: Console
Classifier: Intended Audience :: System Administrators
Classifier: License :: OSI Approved :: GNU General Public License v3 (GPLv3)
Classifier: Natural Language :: English
Classifier: Operating System :: POSIX :: Linux
Classifier: Programming Language :: Python :: 3
Classifier: Programming Language :: Python :: 3.9
Classifier: Programming Language :: Python :: 3.10
Classifier: Programming Language :: Python :: 3.11
Classifier: Programming Language :: Python :: 3.12
Classifier: Programming Language :: Python :: 3.13
Classifier: Topic :: System :: Filesystems
Classifier: Topic :: System :: Monitoring
Classifier: Typing :: Typed
Requires-Dist: pydantic-settings (==2.9.1)
Requires-Dist: sqlalchemy (==2.0.40)
Project-URL: Documentation, https://crc-pages.pitt.edu/quota_notifier/
Project-URL: Homepage, https://github.com/pitt-crc/quota_notifier
Project-URL: Repository, https://github.com/pitt-crc/quota_notifier
